odoo8_addon_sales_team_security-8.0.1.0.0-py2.7-nspkg.pth
odoo_addons/sales_team_security/__openerp__.py
odoo_addons/sales_team_security/hooks.py
odoo_addons/sales_team_security/__init__.py
odoo_addons/sales_team_security/README.rst
odoo_addons/sales_team_security/security/sales_team_security.xml
odoo_addons/sales_team_security/models/res_partner.py
odoo_addons/sales_team_security/models/__init__.py
odoo_addons/sales_team_security/models/res_users.py
odoo_addons/sales_team_security/views/res_partner_view.xml
odoo_addons/sales_team_security/tests/__init__.py
odoo_addons/sales_team_security/tests/test_sales_team_security.py
odoo_addons/sales_team_security/static/description/icon.png
odoo8_addon_sales_team_security-8.0.1.0.0.dist-info/top_level.txt
odoo8_addon_sales_team_security-8.0.1.0.0.dist-info/WHEEL
odoo8_addon_sales_team_security-8.0.1.0.0.dist-info/RECORD
odoo8_addon_sales_team_security-8.0.1.0.0.dist-info/metadata.json
odoo8_addon_sales_team_security-8.0.1.0.0.dist-info/DESCRIPTION.rst
odoo8_addon_sales_team_security-8.0.1.0.0.dist-info/METADATA
odoo8_addon_sales_team_security-8.0.1.0.0.dist-info/namespace_packages.txt
